airoh/__init__.py
airoh/containers.py
airoh/datalad.py
airoh/utils.py
airoh-0.1.4.dist-info/METADATA
airoh-0.1.4.dist-info/WHEEL
airoh-0.1.4.dist-info/licenses/LICENSE
airoh-0.1.4.dist-info/RECORD
