Metadata-Version: 2.4
Name: airoh
Version: 0.1.4
Summary: A lightweight task library for reproducible workflows
Project-URL: Homepage, https://github.com/simexp/airoh
Project-URL: Issues, https://github.com/SIMEXP/airoh/issues
Author-email: Lune Bellec <lune.bellec@umontreal.ca>
License: MIT
License-File: LICENSE
Requires-Python: >=3.8
Requires-Dist: invoke>=2.0
